mydeen/__init__.py
mydeen/config.py
mydeen/exception_error.py
mydeen/interface.py
mydeen/memory_quran.py
mydeen/meta_quran_reader.py
mydeen/metasurahs.py
mydeen/mydeen.py
mydeen/quran_reader_base.py
mydeen/services.py
mydeen/yt_services.py
mydeen-1.2.3.dist-info/METADATA
mydeen-1.2.3.dist-info/WHEEL
mydeen-1.2.3.dist-info/RECORD
