Metadata-Version: 2.3
Name: mydeen
Version: 1.2.3
Summary: Un package Python qui, par la permission d'Allah, soit un bien pour la communauté musulmane francophone.
License: MIT
Keywords: coran,youtube,islam,python,API,religion
Author: YassinePaquitoNobody
Author-email: monsieurnobody01@gmail.com
Requires-Python: >=3.9
Classifier: License :: OSI Approved :: MIT License
Classifier: Operating System :: OS Independent
Classifier: Programming Language :: Python :: 3
Classifier: Programming Language :: Python :: 3.9
Classifier: Programming Language :: Python :: 3.10
Classifier: Programming Language :: Python :: 3.11
Classifier: Programming Language :: Python :: 3.12
Classifier: Programming Language :: Python :: 3.13
Requires-Dist: httpx (<0.24)
Requires-Dist: pandas (>=2.2.3,<3.0.0)
Requires-Dist: pytube (>=15.0.0,<16.0.0)
Requires-Dist: requests (>=2.32.3,<3.0.0)
Requires-Dist: typing-extensions (>=4.12.2,<5.0.0)
Requires-Dist: youtube-search-python (>=1.6.6,<2.0.0)
Project-URL: Homepage, https://github.com/YassineNobody/mydeen
Project-URL: Repository, https://github.com/YassineNobody/mydeen
